src/__init__.py
src/gsindex.py
gsindex-0.1.0.dist-info/LICENSE
gsindex-0.1.0.dist-info/METADATA
gsindex-0.1.0.dist-info/WHEEL
gsindex-0.1.0.dist-info/top_level.txt
gsindex-0.1.0.dist-info/RECORD
