Metadata-Version: 2.1
Name: gsindex
Version: 0.1.0
Summary: Python wrapper for calculating the geometrical separability index (gsi)
Home-page: https://github.com/aacevedot/gsindex
Author: Aldo Acevedo
Author-email: aldo.acevedo.toledo@gmail.com
License: MIT
Platform: UNKNOWN
Classifier: Intended Audience :: Science/Research
Classifier: License :: OSI Approved :: MIT License
Classifier: Operating System :: OS Independent
Classifier: Programming Language :: Python :: 3
Classifier: Topic :: System :: Clustering
Requires-Python: >=3.8
License-File: LICENSE
Requires-Dist: numpy (>=1.20)
Requires-Dist: scipy (>=1.6)
Provides-Extra: test
Requires-Dist: pytest (>=6.2) ; extra == 'test'
Requires-Dist: flake8 (>=3.9) ; extra == 'test'
